<?xml version="1.0" encoding="utf-8"?>
<i>
  <metadata>
    <platform>Bilibili</platform>
    <video_start_time>1759586869655</video_start_time>
    <live_start_time>1759574013000</live_start_time>
    <user_name>玵木_Anmua-</user_name>
    <room_id>5215238</room_id>
  </metadata>
  <d p="0.689,4,25,14893055,1759586870344,0,8445075,8445075,0" user="一号月球" uid="8445075" timestamp="1759586870344">……</d>
  <d p="5.401,4,25,14893055,1759586875056,0,8445075,8445075,0" user="一号月球" uid="8445075" timestamp="1759586875056">我在城轨</d>
  <d p="13.559,4,25,14893055,1759586883214,0,8445075,8445075,0" user="一号月球" uid="8445075" timestamp="1759586883214">开不了啊</d>
  <d p="14.681,4,25,4546550,1759586884336,0,39112,39112,0" user="猫熊123" uid="39112" timestamp="1759586884336">来一首告白气球</d>
  <d p="17.64,4,25,14893055,1759586887295,0,8445075,8445075,0" user="一号月球" uid="8445075" timestamp="1759586887295">[手机][手机][手机]</d>
  <d p="25.883,1,25,16777215,1759586895538,0,3790248,3790248,0" user="烛愿KS" uid="3790248" timestamp="1759586895538">我呢qwq</d>
  <d p="32.679,4,25,14893055,1759586902334,0,8445075,8445075,0" user="一号月球" uid="8445075" timestamp="1759586902334">后续补上</d>
  <d p="44.863,1,25,16777215,1759586914518,0,3790248,3790248,0" user="烛愿KS" uid="3790248" timestamp="1759586914518">我现在要抽</d>
  <d p="62.455,4,25,14893055,1759586932110,0,8445075,8445075,0" user="一号月球" uid="8445075" timestamp="1759586932110">想要礼物，果然还是太难了[妙]</d>
  <d p="67.217,1,25,16777215,1759586936872,0,3790248,3790248,0" user="烛愿KS" uid="3790248" timestamp="1759586936872">刚才我不是送了10个咩</d>
  <d p="77.436,1,25,16777215,1759586947091,0,3790248,3790248,0" user="烛愿KS" uid="3790248" timestamp="1759586947091">就是打PK的时候</d>
  <d p="149.733,1,25,16777215,1759587019388,0,3790248,3790248,0" user="烛愿KS" uid="3790248" timestamp="1759587019388">祝我发财说是</d>
  <d p="219.027,4,25,16747553,1759587088682,0,14507914,14507914,0" user="申花轨迹" uid="14507914" timestamp="1759587088682">期待[哇]</d>
  <d p="285.953,4,25,14893055,1759587155608,0,8445075,8445075,0" user="一号月球" uid="8445075" timestamp="1759587155608">我这三天cicf用废了三支樱花</d>
  <d p="288.988,4,25,14893055,1759587158643,0,8445075,8445075,0" user="一号月球" uid="8445075" timestamp="1759587158643">[手机][手机][手机]</d>
  <d p="314.829,4,25,14893055,1759587184484,0,8445075,8445075,0" user="一号月球" uid="8445075" timestamp="1759587184484">没有</d>
  <d p="337.988,4,25,14893055,1759587207643,0,8445075,8445075,0" user="一号月球" uid="8445075" timestamp="1759587207643">写了几下就寄了，感觉买了假樱花</d>
  <d p="352.37,4,25,14893055,1759587222025,0,8445075,8445075,0" user="一号月球" uid="8445075" timestamp="1759587222025">不出水，要么颜色不对</d>
  <d p="425.031,4,25,16747553,1759587294686,0,14507914,14507914,0" user="申花轨迹" uid="14507914" timestamp="1759587294686">好耶好耶</d>
  <d p="472.813,4,25,16747553,1759587342468,0,14507914,14507914,0" user="申花轨迹" uid="14507914" timestamp="1759587342468">好了好了</d>
  <d p="478.931,4,25,16747553,1759587348586,0,14507914,14507914,0" user="申花轨迹" uid="14507914" timestamp="1759587348586">[哇][哇]</d>
  <d p="485.061,4,25,16747553,1759587354716,0,14507914,14507914,0" user="申花轨迹" uid="14507914" timestamp="1759587354716">开心开心</d>
  <d p="509.841,1,25,16777215,1759587379496,0,3790248,3790248,0" user="烛愿KS" uid="3790248" timestamp="1759587379496">qwq</d>
  <d p="513.498,1,25,16777215,1759587383153,0,3790248,3790248,0" user="烛愿KS" uid="3790248" timestamp="1759587383153">我在呢</d>
  <d p="558.26,1,25,16772431,1759587427915,0,1969752,1969752,0" user="锦橙守白" uid="1969752" timestamp="1759587427915">[dog]</d>
  <d p="611.972,4,25,16747553,1759587481627,0,14507914,14507914,0" user="申花轨迹" uid="14507914" timestamp="1759587481627">呆呆的小男孩[dog]</d>
  <d p="628.865,1,25,16772431,1759587498520,0,1969752,1969752,0" user="锦橙守白" uid="1969752" timestamp="1759587498520">[舰长_疑惑]</d>
  <d p="646.263,4,25,16747553,1759587515918,0,14507914,14507914,0" user="申花轨迹" uid="14507914" timestamp="1759587515918">修炼</d>
  <d p="653.846,1,25,16777215,1759587523501,0,3790248,3790248,0" user="烛愿KS" uid="3790248" timestamp="1759587523501">太可爱了木木</d>
  <d p="660.241,1,25,16777215,1759587529896,0,3790248,3790248,0" user="烛愿KS" uid="3790248" timestamp="1759587529896">亲一下[害羞][害羞][害羞]</d>
  <d p="669.035,1,25,16777215,1759587538690,0,3790248,3790248,0" user="烛愿KS" uid="3790248" timestamp="1759587538690">陪你到下播呗</d>
  <d p="679.679,1,25,16777215,1759587549334,0,3790248,3790248,0" user="烛愿KS" uid="3790248" timestamp="1759587549334">我给你个图你做参考</d>
  <d p="687.234,1,25,16777215,1759587556889,0,3546688648120684,3546688648120684,0" user="Martini--" uid="3546688648120684" timestamp="1759587556889">哪里有富哥</d>
  <d p="784.911,4,25,14893055,1759587654566,0,24802828,24802828,0" user="也茧" uid="24802828" timestamp="1759587654566">偷摸着看看收获如何</d>
  <d p="815.55,4,25,14893055,1759587685205,0,343393770,343393770,0" user="Brolysia" uid="343393770" timestamp="1759587685205">哇</d>
  <d p="821.425,4,25,14893055,1759587691080,0,343393770,343393770,0" user="Brolysia" uid="343393770" timestamp="1759587691080">刚走一会</d>
  <d p="821.51,1,25,16772431,1759587691165,0,1969752,1969752,0" user="锦橙守白" uid="1969752" timestamp="1759587691165">[舰长_暗中观察]</d>
  <d p="835.239,4,25,14893055,1759587704894,0,343393770,343393770,0" user="Brolysia" uid="343393770" timestamp="1759587704894">又有总督了</d>
  <d p="864.798,1,25,16777215,1759587734453,0,3790248,3790248,0" user="烛愿KS" uid="3790248" timestamp="1759587734453">坏了，最近没啥好看的照片</d>
  <d p="882.937,1,25,16777215,1759587752592,0,3790248,3790248,0" user="烛愿KS" uid="3790248" timestamp="1759587752592">视频里截了张图给你</d>
  <d p="918.065,4,25,16747553,1759587787720,0,14507914,14507914,0" user="申花轨迹" uid="14507914" timestamp="1759587787720">好可爱</d>
  <d p="928.379,1,25,16772431,1759587798034,0,1969752,1969752,0" user="锦橙守白" uid="1969752" timestamp="1759587798034">还真挺像</d>
  <d p="942.769,1,25,16777215,1759587812424,0,3790248,3790248,0" user="烛愿KS" uid="3790248" timestamp="1759587812424">可以把木木画我旁边吗[害羞]（</d>
  <d p="947.296,4,25,14893055,1759587816951,0,283759985,283759985,0" user="莫若奇剑" uid="283759985" timestamp="1759587816951">收到</d>
  <d p="975.552,1,25,16772431,1759587845207,0,275480063,275480063,0" user="诺福克公爵" uid="275480063" timestamp="1759587845207">很有精神</d>
  <d p="1066.181,1,25,16772431,1759587935836,0,1969752,1969752,0" user="锦橙守白" uid="1969752" timestamp="1759587935836">[舰长_暗中观察]</d>
  <d p="1072.859,1,25,16772431,1759587942514,0,1969752,1969752,0" user="锦橙守白" uid="1969752" timestamp="1759587942514">在的</d>
  <d p="1084.601,1,25,16772431,1759587954256,0,1969752,1969752,0" user="锦橙守白" uid="1969752" timestamp="1759587954256">yep</d>
  <d p="1140.89,4,25,16747553,1759588010545,0,14507914,14507914,0" user="申花轨迹" uid="14507914" timestamp="1759588010545">我是不是还有张[dog]</d>
  <d p="1185.604,4,25,14893055,1759588055259,0,283759985,283759985,0" user="莫若奇剑" uid="283759985" timestamp="1759588055259">好好好</d>
  <d p="1202.711,4,25,14893055,1759588072366,0,11542325,11542325,0" user="优瑞可kk" uid="11542325" timestamp="1759588072366">宝礼物放你门口了[dog][dog][dog]拿到了</d>
  <d p="1211.677,4,25,14893055,1759588081332,0,11542325,11542325,0" user="优瑞可kk" uid="11542325" timestamp="1759588081332">可以去拆一下</d>
  <d p="1213.979,4,25,14893055,1759588083634,0,283759985,283759985,0" user="莫若奇剑" uid="283759985" timestamp="1759588083634">当时两句话各抽了两个字</d>
  <d p="1227.687,4,25,14893055,1759588097342,0,283759985,283759985,0" user="莫若奇剑" uid="283759985" timestamp="1759588097342">没啥特殊含义</d>
  <d p="1296.239,4,25,14893055,1759588165894,0,283759985,283759985,0" user="莫若奇剑" uid="283759985" timestamp="1759588165894">木木帮我加朵桃花[花]</d>
  <d p="1416.499,1,25,16772431,1759588286154,0,275480063,275480063,0" user="诺福克公爵" uid="275480063" timestamp="1759588286154">修炼</d>
  <d p="1497.291,4,25,14893055,1759588366946,0,283759985,283759985,0" user="莫若奇剑" uid="283759985" timestamp="1759588366946">桃树是个好东西，桃花象征姻缘，蟠桃象征长寿，雷击木好像也是桃树</d>
  <d p="1520.626,4,25,14893055,1759588390281,0,283759985,283759985,0" user="莫若奇剑" uid="283759985" timestamp="1759588390281">[花]目前很欣赏桃树</d>
  <d p="1617.618,4,25,14893055,1759588487273,0,283759985,283759985,0" user="莫若奇剑" uid="283759985" timestamp="1759588487273">修炼</d>
  <d p="1773.694,4,25,14893055,1759588643349,0,283759985,283759985,0" user="莫若奇剑" uid="283759985" timestamp="1759588643349">谢谢木木</d>
  <d p="1778.972,4,25,14893055,1759588648627,0,283759985,283759985,0" user="莫若奇剑" uid="283759985" timestamp="1759588648627">在的在的</d>
  <d p="1809.291,4,25,14893055,1759588678946,0,283759985,283759985,0" user="莫若奇剑" uid="283759985" timestamp="1759588678946">okok</d>
  <d p="1815.318,4,25,14893055,1759588684973,0,283759985,283759985,0" user="莫若奇剑" uid="283759985" timestamp="1759588684973">谢谢木木</d>
  <d p="1864.807,1,25,16777215,1759588734462,0,3790248,3790248,0" user="烛愿KS" uid="3790248" timestamp="1759588734462">在的[花]</d>
  <d p="1866.599,4,25,14893055,1759588736254,0,8445075,8445075,0" user="一号月球" uid="8445075" timestamp="1759588736254">啊</d>
  <d p="1884.866,4,25,16747553,1759588754521,0,14507914,14507914,0" user="申花轨迹" uid="14507914" timestamp="1759588754521">修炼</d>
  <d p="1893.661,4,25,14893055,1759588763316,0,283759985,283759985,0" user="莫若奇剑" uid="283759985" timestamp="1759588763316">问题不大</d>
  <d p="1900.658,4,25,5816798,1759588770313,0,3546962496326176,3546962496326176,0" user="林兆禛" uid="3546962496326176" timestamp="1759588770313">读真</d>
  <d p="1978.876,1,25,16777215,1759588848531,0,252573910,252573910,0" user="__逞__" uid="252573910" timestamp="1759588848531">生日快乐</d>
  <d p="2027.45,4,25,5816798,1759588897105,0,3546962496326176,3546962496326176,0" user="林兆禛" uid="3546962496326176" timestamp="1759588897105">我就不抽啦</d>
  <d p="2048.476,4,25,5816798,1759588918131,0,3546962496326176,3546962496326176,0" user="林兆禛" uid="3546962496326176" timestamp="1759588918131">嗯</d>
  <d p="2186.349,4,25,5816798,1759589056004,0,319198085,319198085,0" user="兔酱不睡懒觉" uid="319198085" timestamp="1759589056004">ok，</d>
  <d p="2235.03,1,25,16777215,1759589104685,0,3790248,3790248,0" user="烛愿KS" uid="3790248" timestamp="1759589104685">在呢</d>
  <d p="2242.138,1,25,16777215,1759589111793,0,3790248,3790248,0" user="烛愿KS" uid="3790248" timestamp="1759589111793">刚才接了个电话</d>
  <d p="2245.153,1,25,16777215,1759589114808,0,3790248,3790248,0" user="烛愿KS" uid="3790248" timestamp="1759589114808">[萌宠小熊_抱抱]</d>
  <d p="2260.018,1,25,16777215,1759589129673,0,360811416,360811416,0" user="Krozik" uid="360811416" timestamp="1759589129673">生日快乐[比心]</d>
  <d p="2264.188,1,25,16777215,1759589133843,0,3790248,3790248,0" user="烛愿KS" uid="3790248" timestamp="1759589133843">可以把木木画在我旁边吗[害羞]</d>
  <d p="2281.056,1,25,16777215,1759589150711,0,3790248,3790248,0" user="烛愿KS" uid="3790248" timestamp="1759589150711">对的[花][花][花]</d>
  <d p="2305.491,1,25,16777215,1759589175146,0,3790248,3790248,0" user="烛愿KS" uid="3790248" timestamp="1759589175146">我怕有些人搜我b站账号</d>
  <d p="2310.733,4,25,12802438,1759589180388,0,176496478,176496478,0" user="晫雨青云" uid="176496478" timestamp="1759589180388">我基本都是一个名</d>
  <d p="2313.318,1,25,16777215,1759589182973,0,3790248,3790248,0" user="烛愿KS" uid="3790248" timestamp="1759589182973">就改成不一样的了</d>
  <d p="2323.332,4,25,12802438,1759589192987,0,176496478,176496478,0" user="晫雨青云" uid="176496478" timestamp="1759589192987">只改头像</d>
  <d p="2344.488,4,25,12802438,1759589214143,0,176496478,176496478,0" user="晫雨青云" uid="176496478" timestamp="1759589214143">有始有终</d>
  <d p="2364.487,4,25,12802438,1759589234142,0,176496478,176496478,0" user="晫雨青云" uid="176496478" timestamp="1759589234142">我手机号就一个用22年了</d>
  <d p="2379.536,4,25,12802438,1759589249191,0,176496478,176496478,0" user="晫雨青云" uid="176496478" timestamp="1759589249191">小学就开始用了</d>
  <d p="2457.356,1,25,16777215,1759589327011,0,3790248,3790248,0" user="烛愿KS" uid="3790248" timestamp="1759589327011">那很帅了[花]</d>
  <d p="2472.324,4,25,12802438,1759589341979,0,176496478,176496478,0" user="晫雨青云" uid="176496478" timestamp="1759589341979">凶悍刀疤人</d>
  <d p="2538.363,4,25,5816798,1759589408018,0,319198085,319198085,0" user="兔酱不睡懒觉" uid="319198085" timestamp="1759589408018">[花][花][花]</d>
  <d p="2597.181,4,25,12802438,1759589466836,0,176496478,176496478,0" user="晫雨青云" uid="176496478" timestamp="1759589466836">黑长直赛高</d>
  <d p="2630.592,1,25,16777215,1759589500247,0,3790248,3790248,0" user="烛愿KS" uid="3790248" timestamp="1759589500247">爱了</d>
  <d p="2634.414,1,25,16777215,1759589504069,0,3790248,3790248,0" user="烛愿KS" uid="3790248" timestamp="1759589504069">认真的木木</d>
  <d p="2636.287,1,25,16777215,1759589505942,0,3790248,3790248,0" user="烛愿KS" uid="3790248" timestamp="1759589505942">可爱</d>
  <d p="2673.117,4,25,12802438,1759589542772,0,176496478,176496478,0" user="晫雨青云" uid="176496478" timestamp="1759589542772">这是硬朗下颌线</d>
  <d p="2675.367,1,25,16777215,1759589545022,0,3790248,3790248,0" user="烛愿KS" uid="3790248" timestamp="1759589545022">那很可爱了哈哈哈哈</d>
  <d p="2678.474,4,25,14893055,1759589548129,0,8445075,8445075,0" user="一号月球" uid="8445075" timestamp="1759589548129">可以当头像了[dog]</d>
  <d p="2681.477,1,25,16777215,1759589551132,0,226677030,226677030,0" user="月亮尾巴" uid="226677030" timestamp="1759589551132">厉害啊</d>
  <d p="2684.238,1,25,16777215,1759589553893,0,3790248,3790248,0" user="烛愿KS" uid="3790248" timestamp="1759589553893">木木可以比个耶那[比心][害羞]</d>
  <d p="2692.771,1,25,16777215,1759589562426,0,3790248,3790248,0" user="烛愿KS" uid="3790248" timestamp="1759589562426">比个耶我截个图</d>
</i>
