<?xml version="1.0" encoding="utf-8"?>
<i>
  <metadata>
    <platform>Bilibili</platform>
    <video_start_time>1759413283476</video_start_time>
    <live_start_time>1759400413000</live_start_time>
    <user_name>长猫的小明</user_name>
    <room_id>26608186</room_id>
  </metadata>
  <d p="5.384,4,25,4546550,1759413288860,0,2319385,2319385,0" user="KBXXML" uid="2319385" timestamp="1759413288860">老掉牙</d>
  <d p="8.813,4,25,4546550,1759413292289,0,23672871,23672871,0" user="轻舞飞阳-" uid="23672871" timestamp="1759413292289">乡毋宁</d>
  <d p="14.592,4,25,4546550,1759413298068,0,23672871,23672871,0" user="轻舞飞阳-" uid="23672871" timestamp="1759413298068">哈哈哈哈</d>
  <d p="30.223,4,25,12802438,1759413313699,0,28741441,28741441,0" user="哈德曼的妖怪铜板" uid="28741441" timestamp="1759413313699">我嘞个乡毋宁阿</d>
  <d p="69.466,1,25,16777215,1759413352942,0,49586446,49586446,0" user="一個明明" uid="49586446" timestamp="1759413352942">求翻译[dog]</d>
  <d p="69.938,1,25,16777215,1759413353414,0,2051880250,2051880250,0" user="小野小树" uid="2051880250" timestamp="1759413353414">咦居然说成都话了</d>
  <d p="89.545,4,25,4546550,1759413373021,0,2319385,2319385,0" user="KBXXML" uid="2319385" timestamp="1759413373021">我说过，河北人</d>
  <d p="95.657,1,25,16777215,1759413379133,0,2051880250,2051880250,0" user="小野小树" uid="2051880250" timestamp="1759413379133">是我说的</d>
  <d p="98.215,4,25,4546550,1759413381691,0,2319385,2319385,0" user="KBXXML" uid="2319385" timestamp="1759413381691">河北承德</d>
  <d p="117.547,1,25,16777215,1759413401023,0,2051880250,2051880250,0" user="小野小树" uid="2051880250" timestamp="1759413401023">以前也是我说要听你成都话</d>
  <d p="121.309,1,25,16777215,1759413404785,0,2051880250,2051880250,0" user="小野小树" uid="2051880250" timestamp="1759413404785">昨天说的</d>
  <d p="135.091,1,25,16777215,1759413418567,0,2051880250,2051880250,0" user="小野小树" uid="2051880250" timestamp="1759413418567">好嘛</d>
  <d p="145.556,4,25,12802438,1759413429032,0,28741441,28741441,0" user="哈德曼的妖怪铜板" uid="28741441" timestamp="1759413429032">哈哈哈哈哈哈</d>
  <d p="155.666,4,25,4546550,1759413439142,0,23672871,23672871,0" user="轻舞飞阳-" uid="23672871" timestamp="1759413439142">巴适了</d>
  <d p="156.513,1,25,16777215,1759413439989,0,2051880250,2051880250,0" user="小野小树" uid="2051880250" timestamp="1759413439989">还行的</d>
  <d p="195.451,4,25,4546550,1759413478927,0,2319385,2319385,0" user="KBXXML" uid="2319385" timestamp="1759413478927">怎么听出一股唐山味[dog]</d>
  <d p="224.112,1,25,16777215,1759413507588,0,49586446,49586446,0" user="一個明明" uid="49586446" timestamp="1759413507588">广东人</d>
  <d p="226.192,4,25,4546550,1759413509668,0,2319385,2319385,0" user="KBXXML" uid="2319385" timestamp="1759413509668">说话像唱歌，有音律</d>
  <d p="264.582,1,25,5816798,1759413548058,0,170416,170416,0" user="Fubuki" uid="170416" timestamp="1759413548058">主播其实我家一半是川渝人</d>
  <d p="296.772,1,25,5816798,1759413580248,0,170416,170416,0" user="Fubuki" uid="170416" timestamp="1759413580248">我妈我外婆</d>
  <d p="296.786,4,25,4546550,1759413580262,0,2319385,2319385,0" user="KBXXML" uid="2319385" timestamp="1759413580262">像一根柔软弹簧的调调</d>
  <d p="299.687,1,25,5566168,1759413583163,0,1821730332,1821730332,0" user="俨之2011" uid="1821730332" timestamp="1759413583163">还在播啊，这么持久</d>
  <d p="316.647,1,25,5566168,1759413600123,0,1821730332,1821730332,0" user="俨之2011" uid="1821730332" timestamp="1759413600123">手写信？</d>
  <d p="356.525,4,25,12802438,1759413640001,0,28741441,28741441,0" user="哈德曼的妖怪铜板" uid="28741441" timestamp="1759413640001">哈哈哈哈</d>
  <d p="400.454,1,25,5566168,1759413683930,0,1821730332,1821730332,0" user="俨之2011" uid="1821730332" timestamp="1759413683930">哈哈哈哈，你打算给我写什么呢</d>
  <d p="431.669,1,25,5566168,1759413715145,0,1821730332,1821730332,0" user="俨之2011" uid="1821730332" timestamp="1759413715145">那你还是抄课文吧</d>
  <d p="445.064,4,25,12802438,1759413728540,0,28741441,28741441,0" user="哈德曼的妖怪铜板" uid="28741441" timestamp="1759413728540">捏嘿</d>
  <d p="477.872,4,25,4546550,1759413761348,0,23672871,23672871,0" user="轻舞飞阳-" uid="23672871" timestamp="1759413761348">下一个就是出师表了</d>
  <d p="496.837,4,25,12802438,1759413780313,0,28741441,28741441,0" user="哈德曼的妖怪铜板" uid="28741441" timestamp="1759413780313">！</d>
  <d p="503.016,4,25,12802438,1759413786492,0,28741441,28741441,0" user="哈德曼的妖怪铜板" uid="28741441" timestamp="1759413786492">22舰！</d>
  <d p="520.667,4,25,4546550,1759413804143,0,23672871,23672871,0" user="轻舞飞阳-" uid="23672871" timestamp="1759413804143">哇</d>
  <d p="524.471,4,25,4546550,1759413807947,0,23672871,23672871,0" user="轻舞飞阳-" uid="23672871" timestamp="1759413807947">！</d>
  <d p="531.852,1,25,16777215,1759413815328,0,2051880250,2051880250,0" user="小野小树" uid="2051880250" timestamp="1759413815328">明天去干啥为啥不播</d>
  <d p="544.776,4,25,4546550,1759413828252,0,23672871,23672871,0" user="轻舞飞阳-" uid="23672871" timestamp="1759413828252">老板大气老板身体健康，万事如意，心想事成</d>
  <d p="552.3,4,25,4546550,1759413835776,0,2319385,2319385,0" user="KBXXML" uid="2319385" timestamp="1759413835776">散发魅力时刻</d>
  <d p="583.478,4,25,4546550,1759413866954,0,23672871,23672871,0" user="轻舞飞阳-" uid="23672871" timestamp="1759413866954">小鸭鸭～</d>
  <d p="586.597,4,25,4546550,1759413870073,0,2319385,2319385,0" user="KBXXML" uid="2319385" timestamp="1759413870073">牢豆角的神</d>
  <d p="590.649,1,25,16777215,1759413874125,0,49586446,49586446,0" user="一個明明" uid="49586446" timestamp="1759413874125">有毒[笑哭]</d>
  <d p="602.805,4,25,12802438,1759413886281,0,28741441,28741441,0" user="哈德曼的妖怪铜板" uid="28741441" timestamp="1759413886281">豆角之神！</d>
  <d p="604.931,4,25,4546550,1759413888407,0,23672871,23672871,0" user="轻舞飞阳-" uid="23672871" timestamp="1759413888407">豆角好吃</d>
  <d p="617.761,4,25,4546550,1759413901237,0,23672871,23672871,0" user="轻舞飞阳-" uid="23672871" timestamp="1759413901237">可恶</d>
  <d p="626.355,4,25,4546550,1759413909831,0,23672871,23672871,0" user="轻舞飞阳-" uid="23672871" timestamp="1759413909831">歇不了</d>
  <d p="629.491,4,25,12802438,1759413912967,0,28741441,28741441,0" user="哈德曼的妖怪铜板" uid="28741441" timestamp="1759413912967">小小明调休一天吧</d>
  <d p="629.444,4,25,4546550,1759413912920,0,23672871,23672871,0" user="轻舞飞阳-" uid="23672871" timestamp="1759413912920">哈哈哈哈哈</d>
  <d p="656.049,4,25,12802438,1759413939525,0,28741441,28741441,0" user="哈德曼的妖怪铜板" uid="28741441" timestamp="1759413939525">收盲盒的日子哈哈哈</d>
  <d p="660.218,4,25,4546550,1759413943694,0,2319385,2319385,0" user="KBXXML" uid="2319385" timestamp="1759413943694">明天做个美食主播是吧</d>
  <d p="663.195,4,25,4546550,1759413946671,0,23672871,23672871,0" user="轻舞飞阳-" uid="23672871" timestamp="1759413946671">哈哈哈哈</d>
  <d p="692.941,4,25,4546550,1759413976417,0,23672871,23672871,0" user="轻舞飞阳-" uid="23672871" timestamp="1759413976417">放飞自我了</d>
  <d p="725.745,1,25,5816798,1759414009221,0,170416,170416,0" user="Fubuki" uid="170416" timestamp="1759414009221">那拍立得还是明天拍？</d>
  <d p="731.499,4,25,12802438,1759414014975,0,28741441,28741441,0" user="哈德曼的妖怪铜板" uid="28741441" timestamp="1759414014975">哈哈哈哈</d>
  <d p="747.471,4,25,4546550,1759414030947,0,23672871,23672871,0" user="轻舞飞阳-" uid="23672871" timestamp="1759414030947">好忙</d>
  <d p="748.092,1,25,5816798,1759414031568,0,170416,170416,0" user="Fubuki" uid="170416" timestamp="1759414031568">相纸够不</d>
  <d p="750.558,1,25,5816798,1759414034034,0,170416,170416,0" user="Fubuki" uid="170416" timestamp="1759414034034">[Cat2_Watching!]</d>
  <d p="755.112,1,25,16777215,1759414038588,0,176993839,176993839,0" user="筱丶熊熊" uid="176993839" timestamp="1759414038588">你你你</d>
  <d p="760.504,4,25,4546550,1759414043980,0,23672871,23672871,0" user="轻舞飞阳-" uid="23672871" timestamp="1759414043980">可以明明直播我来玩</d>
  <d p="768.438,4,25,4546550,1759414051914,0,23672871,23672871,0" user="轻舞飞阳-" uid="23672871" timestamp="1759414051914">哇哈哈哈</d>
  <d p="794.006,1,25,16777215,1759414077482,0,176993839,176993839,0" user="筱丶熊熊" uid="176993839" timestamp="1759414077482">我跟你说</d>
  <d p="812.163,1,25,16777215,1759414095639,0,176993839,176993839,0" user="筱丶熊熊" uid="176993839" timestamp="1759414095639">头套</d>
  <d p="817.142,4,25,12802438,1759414100618,0,28741441,28741441,0" user="哈德曼的妖怪铜板" uid="28741441" timestamp="1759414100618">乐</d>
  <d p="820.569,4,25,4546550,1759414104045,0,23672871,23672871,0" user="轻舞飞阳-" uid="23672871" timestamp="1759414104045">册</d>
  <d p="839.145,1,25,16777215,1759414122621,0,176993839,176993839,0" user="筱丶熊熊" uid="176993839" timestamp="1759414122621">哈哈哈</d>
  <d p="842.877,4,25,12802438,1759414126353,0,28741441,28741441,0" user="哈德曼的妖怪铜板" uid="28741441" timestamp="1759414126353">没事，明天我在他耳朵边上念一天头套</d>
  <d p="859.518,1,25,16777215,1759414142994,0,176993839,176993839,0" user="筱丶熊熊" uid="176993839" timestamp="1759414142994">都好看的</d>
  <d p="866.169,4,25,12802438,1759414149645,0,28741441,28741441,0" user="哈德曼的妖怪铜板" uid="28741441" timestamp="1759414149645">让熊见证一下黑历史的力量</d>
  <d p="867.814,1,25,5816798,1759414151290,0,170416,170416,0" user="Fubuki" uid="170416" timestamp="1759414151290">穿你那些蕾蕾的ootd呗</d>
  <d p="876.473,4,25,12802438,1759414159949,0,28741441,28741441,0" user="哈德曼的妖怪铜板" uid="28741441" timestamp="1759414159949">对的对的对的</d>
  <d p="880.378,1,25,16777215,1759414163854,0,337107250,337107250,0" user="凉凉汪丶" uid="337107250" timestamp="1759414163854">主包多高</d>
  <d p="889.46,1,25,5816798,1759414172936,0,170416,170416,0" user="Fubuki" uid="170416" timestamp="1759414172936">主包158</d>
  <d p="893.309,4,25,4546550,1759414176785,0,23672871,23672871,0" user="轻舞飞阳-" uid="23672871" timestamp="1759414176785">176</d>
  <d p="902.896,1,25,5816798,1759414186372,0,170416,170416,0" user="Fubuki" uid="170416" timestamp="1759414186372">主包185</d>
  <d p="907.623,4,25,12802438,1759414191099,0,28741441,28741441,0" user="哈德曼的妖怪铜板" uid="28741441" timestamp="1759414191099">主包160</d>
  <d p="921.015,1,25,16777215,1759414204491,0,176993839,176993839,0" user="筱丶熊熊" uid="176993839" timestamp="1759414204491">我咋感觉你，</d>
  <d p="937.975,1,25,16777215,1759414221451,0,176993839,176993839,0" user="筱丶熊熊" uid="176993839" timestamp="1759414221451">164</d>
  <d p="939.162,4,25,12802438,1759414222638,0,28741441,28741441,0" user="哈德曼的妖怪铜板" uid="28741441" timestamp="1759414222638">主包上次说过身高的</d>
  <d p="959.066,4,25,4546550,1759414242542,0,23672871,23672871,0" user="轻舞飞阳-" uid="23672871" timestamp="1759414242542">问就176[dog]</d>
  <d p="968.327,1,25,5816798,1759414251803,0,170416,170416,0" user="Fubuki" uid="170416" timestamp="1759414251803">不猜了 下次偷偷问你</d>
  <d p="976.552,1,25,5816798,1759414260028,0,170416,170416,0" user="Fubuki" uid="170416" timestamp="1759414260028">[Cat2_Watching!]</d>
  <d p="990.197,1,25,16777215,1759414273673,0,243944786,243944786,0" user="Gnqir" uid="243944786" timestamp="1759414273673">168</d>
  <d p="1001.6,4,25,12802438,1759414285076,0,28741441,28741441,0" user="哈德曼的妖怪铜板" uid="28741441" timestamp="1759414285076">什么渣男言论</d>
  <d p="1010.109,1,25,16777215,1759414293585,0,243944786,243944786,0" user="Gnqir" uid="243944786" timestamp="1759414293585">高了还是低了</d>
  <d p="1023.947,1,25,5816798,1759414307423,0,170416,170416,0" user="Fubuki" uid="170416" timestamp="1759414307423">14cm</d>
  <d p="1032.999,1,25,16777215,1759414316475,0,176993839,176993839,0" user="筱丶熊熊" uid="176993839" timestamp="1759414316475">看脸型，172</d>
  <d p="1051.988,1,25,16777215,1759414335464,0,243944786,243944786,0" user="Gnqir" uid="243944786" timestamp="1759414335464">至少18吧</d>
  <d p="1059.358,1,25,5816798,1759414342834,0,170416,170416,0" user="Fubuki" uid="170416" timestamp="1759414342834">主播 我手18</d>
  <d p="1076.917,1,25,16777215,1759414360393,0,243944786,243944786,0" user="Gnqir" uid="243944786" timestamp="1759414360393">怎么可能，手掌加手指这么小</d>
  <d p="1141.563,1,25,16777215,1759414425039,0,176993839,176993839,0" user="筱丶熊熊" uid="176993839" timestamp="1759414425039">十点了，睡吧</d>
  <d p="1175.395,1,25,16777215,1759414458871,0,176993839,176993839,0" user="筱丶熊熊" uid="176993839" timestamp="1759414458871">头套，怨念了</d>
  <d p="1190.195,1,25,5816798,1759414473671,0,170416,170416,0" user="Fubuki" uid="170416" timestamp="1759414473671">TheShy吗</d>
  <d p="1196.785,4,25,12802438,1759414480261,0,28741441,28741441,0" user="哈德曼的妖怪铜板" uid="28741441" timestamp="1759414480261">你还怨念上了</d>
  <d p="1210.377,4,25,12802438,1759414493853,0,28741441,28741441,0" user="哈德曼的妖怪铜板" uid="28741441" timestamp="1759414493853">怎么敢的</d>
  <d p="1213.416,4,25,12802438,1759414496892,0,28741441,28741441,0" user="哈德曼的妖怪铜板" uid="28741441" timestamp="1759414496892">打死</d>
  <d p="1215.799,4,25,4546550,1759414499275,0,23672871,23672871,0" user="轻舞飞阳-" uid="23672871" timestamp="1759414499275">主包你手豪白</d>
  <d p="1255.465,4,25,4546550,1759414538941,0,23672871,23672871,0" user="轻舞飞阳-" uid="23672871" timestamp="1759414538941">羡慕了，我埃及去一趟直接成非洲人了</d>
  <d p="1397.298,1,25,16777215,1759414680774,0,49586446,49586446,0" user="一個明明" uid="49586446" timestamp="1759414680774">静静的听歌[妙]</d>
</i>
