<?xml version="1.0" encoding="utf-8"?>
<i>
  <metadata>
    <platform>Bilibili</platform>
    <video_start_time>1760624557198</video_start_time>
    <live_start_time>1760619154000</live_start_time>
    <user_name>小日和啾</user_name>
    <room_id>3060036</room_id>
  </metadata>
  <d p="2.333,1,25,16777215,1760624559531,0,485983258,485983258,0" user="星月神劫" uid="485983258" timestamp="1760624559531">后面龙王出来了，就龙王更安逸了。[dog]</d>
  <d p="3.693,1,25,16777215,1760624560891,0,3546643058133873,3546643058133873,0" user="招财の肥猫" uid="3546643058133873" timestamp="1760624560891">你已经是成熟的观众了，该学会自己上船了~</d>
  <d p="10.687,1,25,14893055,1760624567885,0,9145507,9145507,0" user="Dazhuuuu" uid="9145507" timestamp="1760624567885">笑死</d>
  <d p="16.606,1,25,14893055,1760624573804,0,492085055,492085055,0" user="霖霜拂月" uid="492085055" timestamp="1760624573804">说完了吗？我要开转了[dog]</d>
  <d p="15.832,4,25,14893055,1760624573030,0,4796140,4796140,0" user="眠海" uid="4796140" timestamp="1760624573030">八重现在优化成一个e三个杀生樱感觉合适</d>
  <d p="18.238,1,25,14893055,1760624575436,0,9145507,9145507,0" user="Dazhuuuu" uid="9145507" timestamp="1760624575436">我知道你是什么时候入坑了</d>
  <d p="35.119,1,25,14893055,1760624592317,0,9145507,9145507,0" user="Dazhuuuu" uid="9145507" timestamp="1760624592317">我在等哥伦比亚</d>
  <d p="42.539,1,25,14893055,1760624599737,0,9145507,9145507,0" user="Dazhuuuu" uid="9145507" timestamp="1760624599737">现在出至冬了吗</d>
  <d p="78.776,1,25,14893055,1760624635974,0,9145507,9145507,0" user="Dazhuuuu" uid="9145507" timestamp="1760624635974">最近几个大版本我除了枫丹音乐很喜欢 火神的那个大版本就不太想玩</d>
  <d p="84.097,1,25,14893055,1760624641295,0,492085055,492085055,0" user="霖霜拂月" uid="492085055" timestamp="1760624641295">钟离开盾，芙芙eq，万叶e，龙王eq，开转</d>
  <d p="87.462,1,25,14893055,1760624644660,0,9145507,9145507,0" user="Dazhuuuu" uid="9145507" timestamp="1760624644660">？卧槽</d>
  <d p="98.259,1,25,14893055,1760624655457,0,9145507,9145507,0" user="Dazhuuuu" uid="9145507" timestamp="1760624655457">出了和我说</d>
  <d p="98.946,1,25,14893055,1760624656144,0,492085055,492085055,0" user="霖霜拂月" uid="492085055" timestamp="1760624656144">潮水啊，我已回来[dog]</d>
  <d p="113.548,1,25,14893055,1760624670746,0,9145507,9145507,0" user="Dazhuuuu" uid="9145507" timestamp="1760624670746">我玩这游戏就是为了抽雷电将军和哥伦比亚</d>
  <d p="130.115,1,25,14893055,1760624687313,0,9145507,9145507,0" user="Dazhuuuu" uid="9145507" timestamp="1760624687313">好 cos给你看</d>
</i>
