<?xml version="1.0" encoding="utf-8"?>
<i>
  <metadata>
    <platform>Bilibili</platform>
    <video_start_time>1759497548072</video_start_time>
    <live_start_time>1759489605000</live_start_time>
    <user_name>小日和啾</user_name>
    <room_id>3060036</room_id>
  </metadata>
  <d p="43.042,4,25,14893055,1759497591114,0,385733647,385733647,0" user="罪了个恶" uid="385733647" timestamp="1759497591114">那包赚不了的</d>
  <d p="66.439,1,25,16772431,1759497614511,0,219999852,219999852,0" user="霏龙蒽葆" uid="219999852" timestamp="1759497614511">国庆快乐</d>
  <d p="69.527,1,25,16777215,1759497617599,0,3546643058133873,3546643058133873,0" user="招财の肥猫" uid="3546643058133873" timestamp="1759497617599">欢迎舰长唯爱心承诺光临！</d>
  <d p="70.513,1,25,16777215,1759497618585,0,3546643058133873,3546643058133873,0" user="招财の肥猫" uid="3546643058133873" timestamp="1759497618585">谢谢-别开腔自己人-爱心抱枕、电影票、棉</d>
  <d p="71.49,1,25,16777215,1759497619562,0,3546643058133873,3546643058133873,0" user="招财の肥猫" uid="3546643058133873" timestamp="1759497619562">花糖</d>
  <d p="72.581,1,25,16777215,1759497620653,0,3546643058133873,3546643058133873,0" user="招财の肥猫" uid="3546643058133873" timestamp="1759497620653">盲盒亏21元</d>
  <d p="84.159,1,25,16777215,1759497632231,0,3546643058133873,3546643058133873,0" user="招财の肥猫" uid="3546643058133873" timestamp="1759497632231">谢谢唯爱心承诺爱心抱枕</d>
  <d p="85.188,1,25,16777215,1759497633260,0,3546643058133873,3546643058133873,0" user="招财の肥猫" uid="3546643058133873" timestamp="1759497633260">盲盒赚1元</d>
  <d p="91.557,4,25,14893055,1759497639629,0,385733647,385733647,0" user="罪了个恶" uid="385733647" timestamp="1759497639629">取得好哇</d>
  <d p="128.918,4,25,14893055,1759497676990,0,385733647,385733647,0" user="罪了个恶" uid="385733647" timestamp="1759497676990">晚上睡觉前看完第三集</d>
  <d p="133.368,4,25,14893055,1759497681440,0,4862421,4862421,0" user="唯爱心承诺" uid="4862421" timestamp="1759497681440">[花]欢迎收看大黑蛋啾</d>
  <d p="138.58,4,25,14893055,1759497686652,0,385733647,385733647,0" user="罪了个恶" uid="385733647" timestamp="1759497686652">你会改观的</d>
  <d p="140.225,1,25,16772431,1759497688297,0,219999852,219999852,0" user="霏龙蒽葆" uid="219999852" timestamp="1759497688297">记得之前看这里有个ID叫“小恶罪啾”</d>
  <d p="159.076,4,25,14893055,1759497707148,0,385733647,385733647,0" user="罪了个恶" uid="385733647" timestamp="1759497707148">你好</d>
  <d p="165.607,1,25,16772431,1759497713679,0,219999852,219999852,0" user="霏龙蒽葆" uid="219999852" timestamp="1759497713679">好家伙</d>
  <d p="180.987,1,25,16772431,1759497729059,0,219999852,219999852,0" user="霏龙蒽葆" uid="219999852" timestamp="1759497729059">这位同志你好</d>
  <d p="187.227,4,25,14893055,1759497735299,0,385733647,385733647,0" user="罪了个恶" uid="385733647" timestamp="1759497735299">我只是回归本我</d>
  <d p="194.454,4,25,14893055,1759497742526,0,385733647,385733647,0" user="罪了个恶" uid="385733647" timestamp="1759497742526">你好同志</d>
  <d p="210.358,4,25,16747553,1759497758430,0,12345072,12345072,0" user="执心老婆" uid="12345072" timestamp="1759497758430">主播玩手机到3点，5点半醒</d>
</i>
