<?xml version="1.0" encoding="utf-8"?>
<i>
  <metadata>
    <platform>Bilibili</platform>
    <video_start_time>1758991256723</video_start_time>
    <live_start_time>1758988110000</live_start_time>
    <user_name>温黎Aliy</user_name>
    <room_id>6705919</room_id>
  </metadata>
  <d p="43.281,1,25,16777215,1758991300004,0,17369923,17369923,0" user="最爱给路灯装挂饰" uid="17369923" timestamp="1758991300004">免费？</d>
  <d p="102.979,1,25,16777215,1758991359702,0,17369923,17369923,0" user="最爱给路灯装挂饰" uid="17369923" timestamp="1758991359702">麦晓雯的要多少钱？</d>
  <d p="111.797,1,25,9920249,1758991368520,0,3919702,3919702,0" user="ReBetta丶律" uid="3919702" timestamp="1758991368520">看人品</d>
  <d p="152.93,1,25,16777215,1758991409653,0,17369923,17369923,0" user="最爱给路灯装挂饰" uid="17369923" timestamp="1758991409653">贴多少？</d>
  <d p="170.911,1,25,4546550,1758991427634,0,66714606,66714606,0" user="芽-Mei" uid="66714606" timestamp="1758991427634">免费啊</d>
  <d p="180.187,1,25,4546550,1758991436910,0,66714606,66714606,0" user="芽-Mei" uid="66714606" timestamp="1758991436910">周年庆还有送的三角券</d>
  <d p="179.826,1,25,4546550,1758991436549,0,291394666,291394666,0" user="柳莲书生" uid="291394666" timestamp="1758991436549">活动坐满了不用贴，周年庆3900</d>
  <d p="183.782,1,25,4546550,1758991440505,0,66714606,66714606,0" user="芽-Mei" uid="66714606" timestamp="1758991440505">加上就免费</d>
  <d p="263.156,1,25,4546550,1758991519879,0,66714606,66714606,0" user="芽-Mei" uid="66714606" timestamp="1758991519879">胳膊不疼</d>
  <d p="342.817,1,25,16777215,1758991599540,0,17369923,17369923,0" user="最爱给路灯装挂饰" uid="17369923" timestamp="1758991599540">保险不吃？</d>
  <d p="356.454,1,25,4546550,1758991613177,0,66714606,66714606,0" user="芽-Mei" uid="66714606" timestamp="1758991613177">楼下有个面包</d>
  <d p="433.41,1,25,16777215,1758991690133,0,17369923,17369923,0" user="最爱给路灯装挂饰" uid="17369923" timestamp="1758991690133">0？</d>
  <d p="599.777,1,25,4546550,1758991856500,0,66714606,66714606,0" user="芽-Mei" uid="66714606" timestamp="1758991856500">大雾模式</d>
  <d p="705.484,1,25,5566168,1758991962207,0,23180414,23180414,0" user="旁边的白" uid="23180414" timestamp="1758991962207">晚上好喵</d>
  <d p="710.544,1,25,5566168,1758991967267,0,23180414,23180414,0" user="旁边的白" uid="23180414" timestamp="1758991967267">晚安喵</d>
  <d p="721.124,1,25,4546550,1758991977847,0,66714606,66714606,0" user="芽-Mei" uid="66714606" timestamp="1758991977847">睡大觉 晚安喵</d>
  <d p="748.111,1,25,4546550,1758992004834,0,66714606,66714606,0" user="芽-Mei" uid="66714606" timestamp="1758992004834">在家是这样的</d>
  <d p="750.034,1,25,16777215,1758992006757,0,17369923,17369923,0" user="最爱给路灯装挂饰" uid="17369923" timestamp="1758992006757">我嘞个煤气罐啊[dog]</d>
  <d p="753.16,1,25,4546550,1758992009883,0,66714606,66714606,0" user="芽-Mei" uid="66714606" timestamp="1758992009883">那狸妈养我喵</d>
  <d p="878.588,1,25,16777215,1758992135311,0,17369923,17369923,0" user="最爱给路灯装挂饰" uid="17369923" timestamp="1758992135311">直升机平台没吃吧</d>
  <d p="978.712,1,25,16777215,1758992235435,0,17369923,17369923,0" user="最爱给路灯装挂饰" uid="17369923" timestamp="1758992235435">你二倒</d>
  <d p="1243.244,1,25,4546550,1758992499967,0,291394666,291394666,0" user="柳莲书生" uid="291394666" timestamp="1758992499967">好想去狙击狸子[dog]</d>
  <d p="1635.039,1,25,5566168,1758992891762,0,312796872,312796872,0" user="常轨脱离Creative" uid="312796872" timestamp="1758992891762">早上好喵</d>
  <d p="1666.338,1,25,5566168,1758992923061,0,312796872,312796872,0" user="常轨脱离Creative" uid="312796872" timestamp="1758992923061">亏了喵</d>
  <d p="1700.045,1,25,5566168,1758992956768,0,312796872,312796872,0" user="常轨脱离Creative" uid="312796872" timestamp="1758992956768">亏了3.5</d>
  <d p="1879.374,1,25,4546550,1758993136097,0,1384354623,1384354623,0" user="琉卡蒂璃斯" uid="1384354623" timestamp="1758993136097">我玩的时候金笔好多</d>
  <d p="1991.459,1,25,5816798,1758993248182,0,259179966,259179966,0" user="小泠家の狗" uid="259179966" timestamp="1758993248182">owo</d>
  <d p="1998.442,1,25,5816798,1758993255165,0,259179966,259179966,0" user="小泠家の狗" uid="259179966" timestamp="1758993255165">我也要玩水煮电喵</d>
  <d p="2064.284,1,25,5566168,1758993321007,0,33411801,33411801,0" user="东方洛十七" uid="33411801" timestamp="1758993321007">早上好</d>
  <d p="2071.386,1,25,5566168,1758993328109,0,33411801,33411801,0" user="东方洛十七" uid="33411801" timestamp="1758993328109">我炸鱼回来了</d>
  <d p="2085.158,1,25,5566168,1758993341881,0,33411801,33411801,0" user="东方洛十七" uid="33411801" timestamp="1758993341881">加了一晚上打了四百多分</d>
  <d p="2123.126,1,25,5566168,1758993379849,0,33411801,33411801,0" user="东方洛十七" uid="33411801" timestamp="1758993379849">[妙]炸鱼是我保持对卡丘热情的唯一方式</d>
  <d p="2171.247,1,25,4546550,1758993427970,0,291394666,291394666,0" user="柳莲书生" uid="291394666" timestamp="1758993427970">航天基地[dog]</d>
  <d p="2447.248,1,25,4546550,1758993703971,0,291394666,291394666,0" user="柳莲书生" uid="291394666" timestamp="1758993703971">要油去航天啊，你都不去要什么要</d>
</i>
