<?xml version="1.0" encoding="utf-8"?>
<i>
  <metadata>
    <platform>Bilibili</platform>
    <video_start_time>1755945467270</video_start_time>
    <live_start_time>1755942558000</live_start_time>
    <user_name>瑞奇咕噜</user_name>
    <room_id>1756267471</room_id>
  </metadata>
  <d p="79.821,1,25,16777215,1755945547091,0,3546794652862635,3546794652862635,0" user="鲤鱼的忠实粉丝1" uid="3546794652862635" timestamp="1755945547091">确实不算很久[妙],但主播注意身体</d>
  <d p="392.472,1,25,5566168,1755945859742,0,3546950817286899,3546950817286899,0" user="是休止呀" uid="3546950817286899" timestamp="1755945859742">也是8级了</d>
  <d p="410.271,1,25,16777215,1755945877541,0,3546794652862635,3546794652862635,0" user="鲤鱼的忠实粉丝1" uid="3546794652862635" timestamp="1755945877541">是这首歌呀，好好听</d>
  <d p="627.153,1,25,16777215,1755946094423,0,3546794652862635,3546794652862635,0" user="鲤鱼的忠实粉丝1" uid="3546794652862635" timestamp="1755946094423">我现在在吃饭[dog]</d>
  <d p="981.519,1,25,16777215,1755946448789,0,3546794652862635,3546794652862635,0" user="鲤鱼的忠实粉丝1" uid="3546794652862635" timestamp="1755946448789">我现在1级都没有，因为我没有钱[委屈]</d>
  <d p="1092.256,1,25,16777215,1755946559526,0,3546794652862635,3546794652862635,0" user="鲤鱼的忠实粉丝1" uid="3546794652862635" timestamp="1755946559526">看来做动画也是一门技术活</d>
  <d p="1138.577,1,25,5566168,1755946605847,0,3546605829490822,3546605829490822,0" user="-初-晴" uid="3546605829490822" timestamp="1755946605847">我在打游戏[吃瓜]</d>
  <d p="1152.085,1,25,16777215,1755946619355,0,3546727367838562,3546727367838562,0" user="bili_55188451555" uid="3546727367838562" timestamp="1755946619355">加油</d>
  <d p="1232.055,1,25,16777215,1755946699325,0,3546794652862635,3546794652862635,0" user="鲤鱼的忠实粉丝1" uid="3546794652862635" timestamp="1755946699325">主播，为什么你不能用番茄小说那个页面还不是可以看，为什么要抄下来呢,最后可以把</d>
  <d p="1237.276,1,25,16777215,1755946704546,0,3546794652862635,3546794652862635,0" user="鲤鱼的忠实粉丝1" uid="3546794652862635" timestamp="1755946704546">名字改下</d>
  <d p="1343.693,1,25,5566168,1755946810963,0,3546950817286899,3546950817286899,0" user="是休止呀" uid="3546950817286899" timestamp="1755946810963">没事的，只要你4连了也一样的</d>
  <d p="1390.989,1,25,16777215,1755946858259,0,3546794652862635,3546794652862635,0" user="鲤鱼的忠实粉丝1" uid="3546794652862635" timestamp="1755946858259">真的吗？[爱]</d>
  <d p="1412.898,1,25,16777215,1755946880168,0,3546794652862635,3546794652862635,0" user="鲤鱼的忠实粉丝1" uid="3546794652862635" timestamp="1755946880168">给你点关注了</d>
  <d p="1597.126,1,25,5566168,1755947064396,0,3546950817286899,3546950817286899,0" user="是休止呀" uid="3546950817286899" timestamp="1755947064396">只要你热爱，其实就很好了</d>
</i>
